tw_stock
