Metadata-Version: 2.1
Name: tw-stock
Version: 1.0.6
Summary: Get Taiwan's stock info in real-time
Home-page: https://github.com/jiunway/tw_stock
Author: Jasper
Author-email: jiunway@gmail.com
Maintainer: Jasper
Maintainer-email: jiunway@gmail.com
License: MIT
Keywords: stock,tw,taiwan stock
Platform: all
